artless_core.py
artless_core-0.4.1.dist-info/licenses/LICENSE
artless_core-0.4.1.dist-info/METADATA
artless_core-0.4.1.dist-info/WHEEL
artless_core-0.4.1.dist-info/top_level.txt
artless_core-0.4.1.dist-info/RECORD
