Metadata-Version: 2.4
Name: artless-core
Version: 0.4.1
Summary: The artless and ultralight web framework for building minimal APIs and apps.
Author-email: Peter Bro <p3t3rbr0@gmail.com>
Maintainer-email: Peter Bro <p3t3rbr0@gmail.com>
License-Expression: MIT
Project-URL: Homepage, https://git.peterbro.su/peter/py3-artless-core
Project-URL: Repository, https://git.peterbro.su/peter/py3-artless-core.git
Project-URL: Issues, https://git.peterbro.su/peter/py3-artless-core/issues
Project-URL: Documentation, https://pages.peterbro.su/py3-artless-core/
Project-URL: Changelog, https://pages.peterbro.su/py3-artless-core/changelog.html
Keywords: artless,ultralight,asgi,wsgi,web,library,framework
Classifier: Development Status :: 4 - Beta
Classifier: Environment :: Web Environment
Classifier: Intended Audience :: Developers
Classifier: Operating System :: OS Independent
Classifier: Programming Language :: Python :: 3
Classifier: Programming Language :: Python :: 3.11
Classifier: Programming Language :: Python :: 3.12
Classifier: Programming Language :: Python :: 3.13
Classifier: Topic :: Internet :: WWW/HTTP
Classifier: Topic :: Internet :: WWW/HTTP :: WSGI :: Application
Classifier: Topic :: Software Development
Classifier: Topic :: Software Development :: Libraries
Classifier: Topic :: Software Development :: Libraries :: Python Modules
Classifier: Topic :: Software Development :: Libraries :: Application Frameworks
Classifier: Typing :: Typed
Requires-Python: >=3.11
License-File: LICENSE
Provides-Extra: build
Requires-Dist: build==1.2.2.post1; extra == "build"
Requires-Dist: twine==6.1.0; extra == "build"
Provides-Extra: dev
Requires-Dist: black==25.1.0; extra == "dev"
Requires-Dist: coverage==7.8.2; extra == "dev"
Requires-Dist: flake8==7.2.0; extra == "dev"
Requires-Dist: isort==6.0.1; extra == "dev"
Requires-Dist: mypy==1.16.0; extra == "dev"
Provides-Extra: benchmarks
Requires-Dist: Django==5.2.2; extra == "benchmarks"
Requires-Dist: Flask==3.1.1; extra == "benchmarks"
Requires-Dist: blacksheep==2.3.1; extra == "benchmarks"
Requires-Dist: bottle==0.13.3; extra == "benchmarks"
Requires-Dist: falcon==4.0.2; extra == "benchmarks"
Requires-Dist: fastapi==0.115.12; extra == "benchmarks"
Requires-Dist: gunicorn==23.0.0; extra == "benchmarks"
Requires-Dist: uvicorn==0.34.3; extra == "benchmarks"
Dynamic: license-file
